{
    "machine": "assembler_standard",
    "registryName": "as_moduleproduct3",
    "recipeTime": 1600,
    "requirements": [
        {
            "type": "energy",
            "io-type": "input",
            "energyPerTick": 350
        },
        {
            "type": "item",
            "io-type": "input",
            "item": "mekanism:controlcircuit@2",
            "amount": 5
        },
        {
            "type": "item",
            "io-type": "input",
            "item": "mekanism:controlcircuit@3",
            "amount": 5
        },
        {
            "type": "item",
            "io-type": "input",
            "item": "minecraft:concrete_powder@1",
            "amount": 5
        },
        {
            "type": "item",
            "io-type": "output",
            "item": "minecraft:concrete_powder@2",
            "amount": 1
        }
    ]
}